odoo/addons/endpoint/README.rst
odoo/addons/endpoint/__init__.py
odoo/addons/endpoint/__manifest__.py
odoo/addons/endpoint/controllers/__init__.py
odoo/addons/endpoint/controllers/main.py
odoo/addons/endpoint/data/server_action.xml
odoo/addons/endpoint/demo/endpoint_demo.xml
odoo/addons/endpoint/i18n/endpoint.pot
odoo/addons/endpoint/i18n/fr.po
odoo/addons/endpoint/i18n/it.po
odoo/addons/endpoint/i18n/zh_CN.po
odoo/addons/endpoint/migrations/18.0.1.0.0/post-migrate.py
odoo/addons/endpoint/models/__init__.py
odoo/addons/endpoint/models/endpoint_endpoint.py
odoo/addons/endpoint/models/endpoint_mixin.py
odoo/addons/endpoint/readme/CONFIGURE.md
odoo/addons/endpoint/readme/CONTRIBUTORS.md
odoo/addons/endpoint/readme/DESCRIPTION.md
odoo/addons/endpoint/readme/ROADMAP.md
odoo/addons/endpoint/security/ir.model.access.csv
odoo/addons/endpoint/security/ir_rule.xml
odoo/addons/endpoint/static/description/icon.png
odoo/addons/endpoint/static/description/index.html
odoo/addons/endpoint/tests/__init__.py
odoo/addons/endpoint/tests/common.py
odoo/addons/endpoint/tests/test_endpoint.py
odoo/addons/endpoint/tests/test_endpoint_controller.py
odoo/addons/endpoint/views/endpoint_view.xml
odoo_addon_endpoint-18.0.1.1.1.dist-info/METADATA
odoo_addon_endpoint-18.0.1.1.1.dist-info/WHEEL
odoo_addon_endpoint-18.0.1.1.1.dist-info/top_level.txt
odoo_addon_endpoint-18.0.1.1.1.dist-info/RECORD
